socialshield/__init__.py
socialshield/loader.py
socialshield-0.1.1.dist-info/METADATA
socialshield-0.1.1.dist-info/WHEEL
socialshield-0.1.1.dist-info/top_level.txt
socialshield-0.1.1.dist-info/RECORD
