Metadata-Version: 2.1
Name: socialshield
Version: 0.1.1
Summary: Demo library
Home-page: https://medium-multiply.readthedocs.io/
Author: Rohith Syam
Author-email: rohithlayana@gmail.com
License: MIT
Classifier: Intended Audience :: Developers
Classifier: License :: OSI Approved :: MIT License
Classifier: Programming Language :: Python
Classifier: Programming Language :: Python :: 3
Classifier: Programming Language :: Python :: 3.6
Classifier: Programming Language :: Python :: 3.7
Classifier: Programming Language :: Python :: 3.8
Classifier: Programming Language :: Python :: 3.9
Classifier: Operating System :: OS Independent
Requires-Dist: numpy
